barcadia/__init__.py
barcadia/cli.py
barcadia/config_utils.py
barcadia/filter_utils.py
barcadia/generate_barcodes.py
barcadia/validate_barcodes.py
barcadia/tools/generate_random_sequences.py
barcadia/tools/memory_benchmark.py
barcadia-3.3.1.dist-info/licenses/LICENSE
barcadia-3.3.1.dist-info/METADATA
barcadia-3.3.1.dist-info/WHEEL
barcadia-3.3.1.dist-info/entry_points.txt
barcadia-3.3.1.dist-info/top_level.txt
barcadia-3.3.1.dist-info/RECORD
