Metadata-Version: 2.4
Name: barcadia
Version: 3.3.1
Summary: A high-performance, memory-efficient toolkit for fast generation and validation of large-scale NGS barcodes
Author: Danting Jiang
License-Expression: Apache-2.0
Project-URL: Repository, https://github.com/djiang0825/NGS_barcode
Project-URL: PyPI, https://pypi.org/project/barcadia/
Keywords: bioinformatics,NGS,barcodes
Classifier: Development Status :: 5 - Production/Stable
Classifier: Intended Audience :: Science/Research
Classifier: Topic :: Scientific/Engineering :: Bio-Informatics
Classifier: Environment :: Console
Classifier: Programming Language :: Python :: 3 :: Only
Classifier: Programming Language :: Python :: 3.12
Classifier: Operating System :: POSIX :: Linux
Classifier: Operating System :: MacOS :: MacOS X
Classifier: Natural Language :: English
Requires-Python: >=3.12
License-File: LICENSE
Requires-Dist: numpy==2.2.6
Requires-Dist: numba==0.61.2
Requires-Dist: llvmlite==0.44.0
Requires-Dist: psutil==7.0.0
Provides-Extra: dev
Requires-Dist: ruff; extra == "dev"
Dynamic: license-file
